<?xml version="1.0" encoding="utf-8"?>
<openerp>
    <data>
        <record id="view_account_invoice_report_brand_graph" model="ir.ui.view">
             <field name="name">account.invoice.report.brand.graph</field>
             <field name="model">account.invoice.report.filter</field>
             <field name="arch" type="xml">
                 <graph string="Invoices Analysis" type="pivot">
                     <field name="section_id" type="row"/>
                     <field name="date" interval="year" type="col"/>
                     <field name="price_total" type="measure"/>
                 </graph>
             </field>
        </record>

        <!-- analisis de facturas filtrado por marcas -->
        <record id="action_account_invoice_report_filter" model="ir.actions.act_window">
            <field name="name">Invoices Analysis brand</field>
            <field name="res_model">account.invoice.report.filter</field>
            <field name="view_type">form</field>
            <field name="view_mode">graph</field>
            <field name="context">{'search_default_current':1, 'search_default_section_id':1, 'search_default_year': 1}</field>
            <field name="search_view_id" ref="account.view_account_invoice_report_search"/>
            <field name="view_id" ref="view_account_invoice_report_brand_graph"/>
        </record>

        <menuitem action="action_account_invoice_report_filter" id="menu_action_account_invoice_report_filter"
                  name="Invoices Analysis brand" parent="base.next_id_64"/>
    </data>
</openerp>
